{"cameraMode":{"drawMode":0,"name":"Shaded","section":"Shading Mode"},"sceneLighting":false,"audioPlay":false,"sceneViewState":{"m_AlwaysRefresh":false,"showFog":true,"showSkybox":false,"showFlares":true,"showImageEffects":true,"showParticleSystems":true,"showVisualEffectGraphs":true,"m_FxEnabled":true},"in2DMode":false,"pivot":{"x":0.0,"y":1.4520000219345093,"z":0.0},"rotation":{"x":0.16568242013454438,"y":-0.023665856570005418,"z":0.003976698499172926,"w":0.9858788847923279},"size":0.17320509254932404,"orthographic":false}